MANIFEST.in
Makefile.in
README_SETUP.txt
aksetup_helper.py
configure
ez_setup.py
setup.py
PyUblasExt.egg-info/PKG-INFO
PyUblasExt.egg-info/SOURCES.txt
PyUblasExt.egg-info/dependency_links.txt
PyUblasExt.egg-info/native_libs.txt
PyUblasExt.egg-info/not-zip-safe
PyUblasExt.egg-info/requires.txt
PyUblasExt.egg-info/top_level.txt
fortran/daskr/LICENSE
fortran/daskr/README
fortran/daskr/build.sh
fortran/daskr/clean.sh
fortran/daskr/daux.f
fortran/daskr/ddaskr.f
fortran/daskr/dlinpk.f
src/cpp/pyublasext/arpack.hpp
src/cpp/pyublasext/arpack_proto.hpp
src/cpp/pyublasext/bicgstab.hpp
src/cpp/pyublasext/cg.hpp
src/cpp/pyublasext/daskr.hpp
src/cpp/pyublasext/matrix_operator.hpp
src/cpp/pyublasext/umfpack.hpp
src/python/__init__.py
src/wrapper/op_daskr.cpp
src/wrapper/operation.cpp
test/demo.py
test/test.py
test/test_data.py
test/testtools.py