Metadata-Version: 1.0
Name: PyUblasExt
Version: 0.92.4
Summary: Added functionality for PyUblas
Home-page: http://mathema.tician.de/software/pyublas/pyublasext
Author: Andreas Kloeckner
Author-email: inform@tiker.net
License: BSD
Platform: UNKNOWN
Classifier: Development Status :: 4 - Beta
Classifier: Environment :: Console
Classifier: Intended Audience :: Developers
Classifier: Intended Audience :: Science/Research
Classifier: License :: OSI Approved :: BSD License
Classifier: Operating System :: MacOS :: MacOS X
Classifier: Operating System :: POSIX
Classifier: Programming Language :: Python
Classifier: Programming Language :: C++
Classifier: Topic :: Scientific/Engineering
Classifier: Topic :: Scientific/Engineering :: Mathematics
Classifier: Topic :: Utilities
